{
    "1": {
        "Ten": {
            "Signed": {
                "SrcAxeY": "Axes.UnSignedTen[\"1\"]",
                "SrcY": "Axes.UnSignedTen[\"1\"][\"I\"]",
                "X": 1,
                "Y": -2
            },
            "UnSigned": {
                "SrcAxeY": "Axes.SignedTen[\"1\"]",
                "SrcY": "Axes.SignedTen[\"1\"][\"I\"]",
                "X": 2,
                "Y": 1
            }
        },
        "Id": 1,
        "Dec": {
            "Signed": {
                "SrcAxeY": "Axes.UnSignedDec[\"1\"]",
                "SrcY": "Axes.UnSignedDec[\"1\"][\"I\"]",
                "X": 1,
                "Y": -2
            },
            "UnSigned": {
                "SrcAxeY": "Axes.SignedDec[\"1\"]",
                "SrcY": "Axes.SignedDec[\"1\"][\"I\"]",
                "X": 2,
                "Y": 1
            }
        }
    }
}