{
    "width": 14,
    "height": 255,
    "points": [
        [
            0,
            2
        ],
        [
            2,
            8
        ],
        [
            6,
            33
        ],
        [
            14,
            131
        ]
    ],
    "csv": "X,Y\n0,2\n2,8\n6,33\n14,131",
    "svg": {
        "I": "<svg xmlns=\"http://www.w3.org/2000/svg\"\n     width=\"14\" height=\"255\"\n     viewBox=\"0 0 14 255\">\n\n<polyline points=\"0,2 2,8 6,33 14,131\"\n    fill=\"none\"\n    stroke=\"#000000\"\n    stroke-width=\"1\"\n    stroke-linejoin=\"miter\"\n    stroke-linecap=\"butt\" />\n</svg>",
        "E": "<svg xmlns=\"http://www.w3.org/2000/svg\"\n     width=\"14\" height=\"255\"\n     viewBox=\"0 0 14 255\">\n\n<polyline points=\"0,2 2,8 6,33 14,131\"\n    fill=\"none\"\n    stroke=\"#FFFFFF\"\n    stroke-width=\"1\"\n    stroke-linejoin=\"miter\"\n    stroke-linecap=\"butt\" />\n</svg>",
        "O": "<svg xmlns=\"http://www.w3.org/2000/svg\"\n     width=\"14\" height=\"255\"\n     viewBox=\"0 0 14 255\">\n<rect width=\"14\" height=\"255\" fill=\"#FFFFFF\" />\n<polyline points=\"0,2 2,8 6,33 14,131\"\n    fill=\"none\"\n    stroke=\"#000000\"\n    stroke-width=\"1\"\n    stroke-linejoin=\"miter\"\n    stroke-linecap=\"butt\" />\n</svg>",
        "A": "<svg xmlns=\"http://www.w3.org/2000/svg\"\n     width=\"14\" height=\"255\"\n     viewBox=\"0 0 14 255\">\n<rect width=\"14\" height=\"255\" fill=\"#000000\" />\n<polyline points=\"0,2 2,8 6,33 14,131\"\n    fill=\"none\"\n    stroke=\"#FFFFFF\"\n    stroke-width=\"1\"\n    stroke-linejoin=\"miter\"\n    stroke-linecap=\"butt\" />\n</svg>",
        "U": "<svg xmlns=\"http://www.w3.org/2000/svg\"\n     width=\"14\" height=\"255\"\n     viewBox=\"0 0 14 255\">\n<rect width=\"14\" height=\"255\" fill=\"#000000\" />\n<polyline points=\"0,2 2,8 6,33 14,131\"\n    fill=\"none\"\n    stroke=\"#FFFFFF\"\n    stroke-width=\"1\"\n    stroke-linejoin=\"miter\"\n    stroke-linecap=\"butt\" />\n</svg>",
        "V": "<svg xmlns=\"http://www.w3.org/2000/svg\"\n     width=\"14\" height=\"255\"\n     viewBox=\"0 0 14 255\">\n<rect width=\"14\" height=\"255\" fill=\"#FFFFFF\" />\n<polyline points=\"0,2 2,8 6,33 14,131\"\n    fill=\"none\"\n    stroke=\"#000000\"\n    stroke-width=\"1\"\n    stroke-linejoin=\"miter\"\n    stroke-linecap=\"butt\" />\n</svg>"
    },
    "files": {
        "png": {
            "I": "I_AIOO_ud.png",
            "E": "E_AIOO_ud.png",
            "O": "O_AIOO_ud.png",
            "A": "A_AIOO_ud.png",
            "U": "U_AIOO_ud.png",
            "V": "V_AIOO_ud.png"
        },
        "svg": {
            "I": "I_AIOO_ud.svg",
            "E": "E_AIOO_ud.svg",
            "O": "O_AIOO_ud.svg",
            "A": "A_AIOO_ud.svg",
            "U": "U_AIOO_ud.svg",
            "V": "V_AIOO_ud.svg"
        },
        "csv": "AIOO_ud.csv"
    }
}