{
    "width": 14,
    "height": 255,
    "points": [
        [
            0,
            3
        ],
        [
            2,
            10
        ],
        [
            6,
            37
        ],
        [
            14,
            155
        ]
    ],
    "csv": "X,Y\n0,3\n2,10\n6,37\n14,155",
    "svg": {
        "I": "<svg xmlns=\"http://www.w3.org/2000/svg\"\n     width=\"14\" height=\"255\"\n     viewBox=\"0 0 14 255\">\n\n<polyline points=\"0,3 2,10 6,37 14,155\"\n    fill=\"none\"\n    stroke=\"#000000\"\n    stroke-width=\"1\"\n    stroke-linejoin=\"miter\"\n    stroke-linecap=\"butt\" />\n</svg>",
        "E": "<svg xmlns=\"http://www.w3.org/2000/svg\"\n     width=\"14\" height=\"255\"\n     viewBox=\"0 0 14 255\">\n\n<polyline points=\"0,3 2,10 6,37 14,155\"\n    fill=\"none\"\n    stroke=\"#FFFFFF\"\n    stroke-width=\"1\"\n    stroke-linejoin=\"miter\"\n    stroke-linecap=\"butt\" />\n</svg>",
        "O": "<svg xmlns=\"http://www.w3.org/2000/svg\"\n     width=\"14\" height=\"255\"\n     viewBox=\"0 0 14 255\">\n<rect width=\"14\" height=\"255\" fill=\"#FFFFFF\" />\n<polyline points=\"0,3 2,10 6,37 14,155\"\n    fill=\"none\"\n    stroke=\"#000000\"\n    stroke-width=\"1\"\n    stroke-linejoin=\"miter\"\n    stroke-linecap=\"butt\" />\n</svg>",
        "A": "<svg xmlns=\"http://www.w3.org/2000/svg\"\n     width=\"14\" height=\"255\"\n     viewBox=\"0 0 14 255\">\n<rect width=\"14\" height=\"255\" fill=\"#000000\" />\n<polyline points=\"0,3 2,10 6,37 14,155\"\n    fill=\"none\"\n    stroke=\"#FFFFFF\"\n    stroke-width=\"1\"\n    stroke-linejoin=\"miter\"\n    stroke-linecap=\"butt\" />\n</svg>",
        "U": "<svg xmlns=\"http://www.w3.org/2000/svg\"\n     width=\"14\" height=\"255\"\n     viewBox=\"0 0 14 255\">\n\n<polyline points=\"0,3 2,10 6,37 14,155\"\n    fill=\"none\"\n    stroke=\"#FFFFFF\"\n    stroke-width=\"1\"\n    stroke-linejoin=\"miter\"\n    stroke-linecap=\"butt\" />\n</svg>",
        "V": "<svg xmlns=\"http://www.w3.org/2000/svg\"\n     width=\"14\" height=\"255\"\n     viewBox=\"0 0 14 255\">\n\n<polyline points=\"0,3 2,10 6,37 14,155\"\n    fill=\"none\"\n    stroke=\"#000000\"\n    stroke-width=\"1\"\n    stroke-linejoin=\"miter\"\n    stroke-linecap=\"butt\" />\n</svg>"
    },
    "files": {
        "png": {
            "I": "I_EIOE_ud.png",
            "E": "E_EIOE_ud.png",
            "O": "O_EIOE_ud.png",
            "A": "A_EIOE_ud.png",
            "U": "U_EIOE_ud.png",
            "V": "V_EIOE_ud.png"
        },
        "svg": {
            "I": "I_EIOE_ud.svg",
            "E": "E_EIOE_ud.svg",
            "O": "O_EIOE_ud.svg",
            "A": "A_EIOE_ud.svg",
            "U": "U_EIOE_ud.svg",
            "V": "V_EIOE_ud.svg"
        },
        "csv": "EIOE_ud.csv"
    }
}