{
    "width": 14,
    "height": 256,
    "points": [
        [
            0,
            126
        ],
        [
            1,
            122
        ],
        [
            3,
            105
        ],
        [
            7,
            39
        ]
    ],
    "csv": "X,Y\n0,126\n1,122\n3,105\n7,39",
    "svg": {
        "I": "<svg xmlns=\"http://www.w3.org/2000/svg\"\n     width=\"14\" height=\"256\"\n     viewBox=\"0 0 14 256\">\n\n<polyline points=\"0,126 1,122 3,105 7,39\"\n    fill=\"none\"\n    stroke=\"#000000\"\n    stroke-width=\"1\"\n    stroke-linejoin=\"miter\"\n    stroke-linecap=\"butt\" />\n</svg>",
        "E": "<svg xmlns=\"http://www.w3.org/2000/svg\"\n     width=\"14\" height=\"256\"\n     viewBox=\"0 0 14 256\">\n\n<polyline points=\"0,126 1,122 3,105 7,39\"\n    fill=\"none\"\n    stroke=\"#FFFFFF\"\n    stroke-width=\"1\"\n    stroke-linejoin=\"miter\"\n    stroke-linecap=\"butt\" />\n</svg>",
        "O": "<svg xmlns=\"http://www.w3.org/2000/svg\"\n     width=\"14\" height=\"256\"\n     viewBox=\"0 0 14 256\">\n<rect width=\"14\" height=\"256\" fill=\"#FFFFFF\" />\n<polyline points=\"0,126 1,122 3,105 7,39\"\n    fill=\"none\"\n    stroke=\"#000000\"\n    stroke-width=\"1\"\n    stroke-linejoin=\"miter\"\n    stroke-linecap=\"butt\" />\n</svg>",
        "A": "<svg xmlns=\"http://www.w3.org/2000/svg\"\n     width=\"14\" height=\"256\"\n     viewBox=\"0 0 14 256\">\n<rect width=\"14\" height=\"256\" fill=\"#000000\" />\n<polyline points=\"0,126 1,122 3,105 7,39\"\n    fill=\"none\"\n    stroke=\"#FFFFFF\"\n    stroke-width=\"1\"\n    stroke-linejoin=\"miter\"\n    stroke-linecap=\"butt\" />\n</svg>",
        "U": "<svg xmlns=\"http://www.w3.org/2000/svg\"\n     width=\"14\" height=\"256\"\n     viewBox=\"0 0 14 256\">\n\n<polyline points=\"0,126 1,122 3,105 7,39\"\n    fill=\"none\"\n    stroke=\"#000000\"\n    stroke-width=\"1\"\n    stroke-linejoin=\"miter\"\n    stroke-linecap=\"butt\" />\n</svg>",
        "V": "<svg xmlns=\"http://www.w3.org/2000/svg\"\n     width=\"14\" height=\"256\"\n     viewBox=\"0 0 14 256\">\n\n<polyline points=\"0,126 1,122 3,105 7,39\"\n    fill=\"none\"\n    stroke=\"#FFFFFF\"\n    stroke-width=\"1\"\n    stroke-linejoin=\"miter\"\n    stroke-linecap=\"butt\" />\n</svg>"
    },
    "files": {
        "png": {
            "I": "I_IAOE_st.png",
            "E": "E_IAOE_st.png",
            "O": "O_IAOE_st.png",
            "A": "A_IAOE_st.png",
            "U": "U_IAOE_st.png",
            "V": "V_IAOE_st.png"
        },
        "svg": {
            "I": "I_IAOE_st.svg",
            "E": "E_IAOE_st.svg",
            "O": "O_IAOE_st.svg",
            "A": "A_IAOE_st.svg",
            "U": "U_IAOE_st.svg",
            "V": "V_IAOE_st.svg"
        },
        "csv": "IAOE_st.csv"
    }
}