{
    "1": {
        "Ten": {
            "Signed": {
                "SrcAxeY": "Axes.UnSignedTen[\"1\"]",
                "SrcY": "Axes.UnSignedTen[\"1\"][\"E\"]",
                "X": 1,
                "Y": 2
            },
            "UnSigned": {
                "SrcAxeY": "Axes.SignedTen[\"1\"]",
                "SrcY": "Axes.SignedTen[\"1\"][\"E\"]",
                "X": 2,
                "Y": 4
            }
        },
        "Id": 1,
        "Dec": {
            "Signed": {
                "SrcAxeY": "Axes.UnSignedDec[\"1\"]",
                "SrcY": "Axes.UnSignedDec[\"1\"][\"E\"]",
                "X": 1,
                "Y": 2
            },
            "UnSigned": {
                "SrcAxeY": "Axes.SignedDec[\"1\"]",
                "SrcY": "Axes.SignedDec[\"1\"][\"E\"]",
                "X": 2,
                "Y": 4
            }
        },
        "1": {
            "Ten": {
                "Signed": {
                    "Ten": {
                        "X": 1,
                        "Y": 2
                    },
                    "Id": {
                        "X": 1,
                        "Y": 2
                    },
                    "Dec": {
                        "X": 1,
                        "Y": 2
                    }
                },
                "UnSigned": {
                    "Ten": {
                        "X": 2,
                        "Y": 4
                    },
                    "Id": {
                        "X": 2,
                        "Y": 4
                    },
                    "Dec": {
                        "X": 2,
                        "Y": 4
                    }
                }
            },
            "Dec": {
                "Signed": {
                    "Ten": {
                        "X": 1,
                        "Y": 2
                    },
                    "Id": {
                        "X": 1,
                        "Y": 2
                    },
                    "Dec": {
                        "X": 1,
                        "Y": 2
                    }
                },
                "UnSigned": {
                    "Ten": {
                        "X": 2,
                        "Y": 4
                    },
                    "Id": {
                        "X": 2,
                        "Y": 4
                    },
                    "Dec": {
                        "X": 2,
                        "Y": 4
                    }
                }
            }
        }
    },
    "2": {
        "Ten": {
            "Signed": {
                "SrcAxeY": "Axes.UnSignedTen[\"2\"]",
                "SrcY": "Axes.UnSignedTen[\"2\"][\"EA\"]",
                "X": 2,
                "Y": 7
            },
            "UnSigned": {
                "SrcAxeY": "Axes.SignedTen[\"2\"]",
                "SrcY": "Axes.SignedTen[\"2\"][\"EA\"]",
                "X": 4,
                "Y": 15
            }
        },
        "Id": 2,
        "Dec": {
            "Signed": {
                "SrcAxeY": "Axes.UnSignedDec[\"2\"]",
                "SrcY": "Axes.UnSignedDec[\"2\"][\"EA\"]",
                "X": 2,
                "Y": 7
            },
            "UnSigned": {
                "SrcAxeY": "Axes.SignedDec[\"2\"]",
                "SrcY": "Axes.SignedDec[\"2\"][\"EA\"]",
                "X": 4,
                "Y": 15
            }
        },
        "2": {
            "Ten": {
                "Signed": {
                    "Ten": {
                        "X": 2,
                        "Y": 7
                    },
                    "Id": {
                        "X": 2,
                        "Y": 7
                    },
                    "Dec": {
                        "X": 2,
                        "Y": 7
                    }
                },
                "UnSigned": {
                    "Ten": {
                        "X": 4,
                        "Y": 15
                    },
                    "Id": {
                        "X": 4,
                        "Y": 15
                    },
                    "Dec": {
                        "X": 4,
                        "Y": 15
                    }
                }
            },
            "Dec": {
                "Signed": {
                    "Ten": {
                        "X": 2,
                        "Y": 7
                    },
                    "Id": {
                        "X": 2,
                        "Y": 7
                    },
                    "Dec": {
                        "X": 2,
                        "Y": 7
                    }
                },
                "UnSigned": {
                    "Ten": {
                        "X": 4,
                        "Y": 15
                    },
                    "Id": {
                        "X": 4,
                        "Y": 15
                    },
                    "Dec": {
                        "X": 4,
                        "Y": 15
                    }
                }
            }
        }
    },
    "3": {
        "Ten": {
            "Signed": {
                "SrcAxeY": "Axes.UnSignedTen[\"3\"]",
                "SrcY": "Axes.UnSignedTen[\"3\"][\"EAE\"]",
                "X": 4,
                "Y": 28
            },
            "UnSigned": {
                "SrcAxeY": "Axes.SignedTen[\"3\"]",
                "SrcY": "Axes.SignedTen[\"3\"][\"EAE\"]",
                "X": 8,
                "Y": 60
            }
        },
        "Id": 3,
        "Dec": {
            "Signed": {
                "SrcAxeY": "Axes.UnSignedDec[\"3\"]",
                "SrcY": "Axes.UnSignedDec[\"3\"][\"EAE\"]",
                "X": 4,
                "Y": 30
            },
            "UnSigned": {
                "SrcAxeY": "Axes.SignedDec[\"3\"]",
                "SrcY": "Axes.SignedDec[\"3\"][\"EAE\"]",
                "X": 8,
                "Y": 62
            }
        },
        "3": {
            "Ten": {
                "Signed": {
                    "Ten": {
                        "X": 4,
                        "Y": 28
                    },
                    "Id": {
                        "X": 4,
                        "Y": 28
                    },
                    "Dec": {
                        "X": 4,
                        "Y": 28
                    }
                },
                "UnSigned": {
                    "Ten": {
                        "X": 8,
                        "Y": 60
                    },
                    "Id": {
                        "X": 8,
                        "Y": 60
                    },
                    "Dec": {
                        "X": 8,
                        "Y": 60
                    }
                }
            },
            "Dec": {
                "Signed": {
                    "Ten": {
                        "X": 4,
                        "Y": 30
                    },
                    "Id": {
                        "X": 4,
                        "Y": 30
                    },
                    "Dec": {
                        "X": 4,
                        "Y": 30
                    }
                },
                "UnSigned": {
                    "Ten": {
                        "X": 8,
                        "Y": 62
                    },
                    "Id": {
                        "X": 8,
                        "Y": 62
                    },
                    "Dec": {
                        "X": 8,
                        "Y": 62
                    }
                }
            }
        }
    },
    "4": {
        "Ten": {
            "Signed": {
                "SrcAxeY": "Axes.UnSignedTen[\"4\"]",
                "SrcY": "Axes.UnSignedTen[\"4\"][\"EAEO\"]",
                "X": 8,
                "Y": 110
            },
            "UnSigned": {
                "SrcAxeY": "Axes.SignedTen[\"4\"]",
                "SrcY": "Axes.SignedTen[\"4\"][\"EAEO\"]",
                "X": 16,
                "Y": 238
            }
        },
        "Id": 4,
        "Dec": {
            "Signed": {
                "SrcAxeY": "Axes.UnSignedDec[\"4\"]",
                "SrcY": "Axes.UnSignedDec[\"4\"][\"EAEO\"]",
                "X": 8,
                "Y": 108
            },
            "UnSigned": {
                "SrcAxeY": "Axes.SignedDec[\"4\"]",
                "SrcY": "Axes.SignedDec[\"4\"][\"EAEO\"]",
                "X": 16,
                "Y": 236
            }
        },
        "4": {
            "Ten": {
                "Signed": {
                    "Ten": {
                        "X": 8,
                        "Y": 110
                    },
                    "Id": {
                        "X": 8,
                        "Y": 110
                    },
                    "Dec": {
                        "X": 8,
                        "Y": 110
                    }
                },
                "UnSigned": {
                    "Ten": {
                        "X": 16,
                        "Y": 238
                    },
                    "Id": {
                        "X": 16,
                        "Y": 238
                    },
                    "Dec": {
                        "X": 16,
                        "Y": 238
                    }
                }
            },
            "Dec": {
                "Signed": {
                    "Ten": {
                        "X": 8,
                        "Y": 108
                    },
                    "Id": {
                        "X": 8,
                        "Y": 108
                    },
                    "Dec": {
                        "X": 8,
                        "Y": 108
                    }
                },
                "UnSigned": {
                    "Ten": {
                        "X": 16,
                        "Y": 236
                    },
                    "Id": {
                        "X": 16,
                        "Y": 236
                    },
                    "Dec": {
                        "X": 16,
                        "Y": 236
                    }
                }
            }
        }
    }
}