{
    "width": 6,
    "height": 63,
    "points": [
        [
            0,
            1
        ],
        [
            2,
            4
        ],
        [
            6,
            19
        ]
    ],
    "csv": "X,Y\n0,1\n2,4\n6,19",
    "svg": {
        "I": "<svg xmlns=\"http://www.w3.org/2000/svg\"\n     width=\"6\" height=\"63\"\n     viewBox=\"0 0 6 63\">\n\n<polyline points=\"0,1 2,4 6,19\"\n    fill=\"none\"\n    stroke=\"#000000\"\n    stroke-width=\"1\"\n    stroke-linejoin=\"miter\"\n    stroke-linecap=\"butt\" />\n</svg>",
        "E": "<svg xmlns=\"http://www.w3.org/2000/svg\"\n     width=\"6\" height=\"63\"\n     viewBox=\"0 0 6 63\">\n\n<polyline points=\"0,1 2,4 6,19\"\n    fill=\"none\"\n    stroke=\"#FFFFFF\"\n    stroke-width=\"1\"\n    stroke-linejoin=\"miter\"\n    stroke-linecap=\"butt\" />\n</svg>",
        "O": "<svg xmlns=\"http://www.w3.org/2000/svg\"\n     width=\"6\" height=\"63\"\n     viewBox=\"0 0 6 63\">\n<rect width=\"6\" height=\"63\" fill=\"#FFFFFF\" />\n<polyline points=\"0,1 2,4 6,19\"\n    fill=\"none\"\n    stroke=\"#000000\"\n    stroke-width=\"1\"\n    stroke-linejoin=\"miter\"\n    stroke-linecap=\"butt\" />\n</svg>",
        "A": "<svg xmlns=\"http://www.w3.org/2000/svg\"\n     width=\"6\" height=\"63\"\n     viewBox=\"0 0 6 63\">\n<rect width=\"6\" height=\"63\" fill=\"#000000\" />\n<polyline points=\"0,1 2,4 6,19\"\n    fill=\"none\"\n    stroke=\"#FFFFFF\"\n    stroke-width=\"1\"\n    stroke-linejoin=\"miter\"\n    stroke-linecap=\"butt\" />\n</svg>",
        "U": "<svg xmlns=\"http://www.w3.org/2000/svg\"\n     width=\"6\" height=\"63\"\n     viewBox=\"0 0 6 63\">\n<rect width=\"6\" height=\"63\" fill=\"#FFFFFF\" />\n<polyline points=\"0,1 2,4 6,19\"\n    fill=\"none\"\n    stroke=\"#000000\"\n    stroke-width=\"1\"\n    stroke-linejoin=\"miter\"\n    stroke-linecap=\"butt\" />\n</svg>",
        "V": "<svg xmlns=\"http://www.w3.org/2000/svg\"\n     width=\"6\" height=\"63\"\n     viewBox=\"0 0 6 63\">\n<rect width=\"6\" height=\"63\" fill=\"#000000\" />\n<polyline points=\"0,1 2,4 6,19\"\n    fill=\"none\"\n    stroke=\"#FFFFFF\"\n    stroke-width=\"1\"\n    stroke-linejoin=\"miter\"\n    stroke-linecap=\"butt\" />\n</svg>"
    },
    "files": {
        "png": {
            "I": "I_OIE_ut.png",
            "E": "E_OIE_ut.png",
            "O": "O_OIE_ut.png",
            "A": "A_OIE_ut.png",
            "U": "U_OIE_ut.png",
            "V": "V_OIE_ut.png"
        },
        "svg": {
            "I": "I_OIE_ut.svg",
            "E": "E_OIE_ut.svg",
            "O": "O_OIE_ut.svg",
            "A": "A_OIE_ut.svg",
            "U": "U_OIE_ut.svg",
            "V": "V_OIE_ut.svg"
        },
        "csv": "OIE_ut.csv"
    }
}